<?xml version="1.0"?>
<!DOCTYPE hibernate-mapping PUBLIC "-//Hibernate/Hibernate Mapping DTD 3.0//EN"
"http://hibernate.sourceforge.net/hibernate-mapping-3.0.dtd">
<!-- Generated Feb 18, 2016 9:57:32 PM by Hibernate Tools 3.5.0.Final -->
<hibernate-mapping>
    <class name="com.britzj.monopoly.model.persistent.Property" table="PROPERTY">
        <id name="PId" type="int" access="field">
            <column name="PID" />
            <generator class="assigned" />
        </id>
        <property name="PName" type="java.lang.String" access="field">
            <column name="PNAME" />
        </property>
        <property name="PtName" type="java.lang.String">
            <column name="PTNAME" />
        </property>
        <property name="PCost" type="long" access="field">
            <column name="PCOST" />
        </property>
        <property name="PHouseCost" type="long" access="field">
            <column name="PHOUSECOST" />
        </property>
        <property name="PMortageVal" type="long" access="field">
            <column name="PMORTAGEVAL" />
        </property>
        <property name="PRgbColor" type="java.lang.String" access="field">
            <column name="PRGBCOLOR" />
        </property>
        <property name="PPosX" type="int" access="field">
            <column name="PPOSX" />
        </property>
        <property name="PPosY" type="int" access="field">
            <column name="PPOSY" />
        </property>
        <property name="PtOwnable" type="int">
            <column name="PTOWNABLE" />
        </property>
    </class>
</hibernate-mapping>
